myhlcb/__init__.py
myhlcb/hello.py
myhlcb-0.1.1.dist-info/METADATA
myhlcb-0.1.1.dist-info/WHEEL
myhlcb-0.1.1.dist-info/top_level.txt
myhlcb-0.1.1.dist-info/RECORD
