Metadata-Version: 2.1
Name: myhlcb
Version: 0.1.1
Summary: An example package
Author: myhlcb
Author-email: osimple23@email.com
